binary_heap/__init__.py
binary_heap/binary_heap.py
binary_heap/max_heap.py
binary_heap/min_heap.py
binary_heap-1.0.1.dist-info/LICENSE
binary_heap-1.0.1.dist-info/METADATA
binary_heap-1.0.1.dist-info/WHEEL
binary_heap-1.0.1.dist-info/top_level.txt
binary_heap-1.0.1.dist-info/RECORD
