Metadata-Version: 2.1
Name: binary-heap
Version: 1.0.1
Summary: Python functions for working with Binary Heap
Home-page: https://github.com/rameshrvr/binary_heap
Author: Ramesh RV
Author-email: rameshrvr@outlook.com
License: GNU General Public License v3.0
Keywords: binary-heap heap python-heap min-heap max-heap
Platform: All
Classifier: Programming Language :: Python :: 2.6
Classifier: Programming Language :: Python :: 2.7
Classifier: Programming Language :: Python :: 3.5
Classifier: Programming Language :: Python :: 3.6
Classifier: Programming Language :: Python :: 3.7
